{
  "version": "7",
  "dialect": "sqlite",
  "entries": [
    {
      "idx": 0,
      "version": "6",
      "when": 1775758511587,
      "tag": "0000_clammy_stick",
      "breakpoints": true
    },
    {
      "idx": 1,
      "version": "6",
      "when": 1775758879957,
      "tag": "0001_illegal_firebird",
      "breakpoints": true
    },
    {
      "idx": 2,
      "version": "6",
      "when": 1775929272257,
      "tag": "0002_useful_carmella_unuscione",
      "breakpoints": true
    },
    {
      "idx": 3,
      "version": "6",
      "when": 1775934933597,
      "tag": "0003_calm_zaran",
      "breakpoints": true
    }
  ]
}